<annotation>
	<folder>train</folder>
	<filename>frame_2590.jpg</filename>
	<path>D:\Study_Material\ROS\Hand Detection\Hands dataset\hand_dataset\TAMAL\train\frame_2590.jpg</path>
	<source>
		<database>Unknown</database>
	</source>
	<size>
		<width>1280</width>
		<height>720</height>
		<depth>3</depth>
	</size>
	<segmented>0</segmented>
	<object>
		<name>hand</name>
		<pose>Unspecified</pose>
		<truncated>0</truncated>
		<difficult>0</difficult>
		<bndbox>
			<xmin>414</xmin>
			<ymin>412</ymin>
			<xmax>594</xmax>
			<ymax>593</ymax>
		</bndbox>
	</object>
	<object>
		<name>hand</name>
		<pose>Unspecified</pose>
		<truncated>0</truncated>
		<difficult>0</difficult>
		<bndbox>
			<xmin>647</xmin>
			<ymin>21</ymin>
			<xmax>793</xmax>
			<ymax>207</ymax>
		</bndbox>
	</object>
	<object>
		<name>hand</name>
		<pose>Unspecified</pose>
		<truncated>0</truncated>
		<difficult>0</difficult>
		<bndbox>
			<xmin>680</xmin>
			<ymin>478</ymin>
			<xmax>1069</xmax>
			<ymax>704</ymax>
		</bndbox>
	</object>
</annotation>
